CacheMemoryProjectAlt/memoryProject_with_main_memory.v
module memoryProject(clk);
    
    //parameters
    parameter sizeOfAddress = 32;
    parameter byteToBits    = 8; //which is also equal to number of bits of size of data
    
    parameter k                  = 8;                                                                        //k-way set associative cache
    parameter bitsOfk            = 3;                                                                    // log2(k)
    parameter index              = 64;
    parameter bitsOfIndex        = 6;                                                                // log2(index)
    parameter blockSize          = 2;                                                                  //number of bytes in a block
    parameter wordSize           = 1;                                                                  //number of bytes in a block
    parameter bitsOfBlockSize    = 1;
    parameter tag                = sizeOfAddress- bitsOfIndex-bitsOfBlockSize;                             //
    parameter cacheElementSize   = 1+ tag + blockSize*byteToBits;                             //  | validBit | Tag | Data |
    parameter instructionSize    = 1 + sizeOfAddress + wordSize*byteToBits;                             //  | read/write | Address | Data(word) |
    parameter instructionMemSize = 524; //
    parameter mainMemorySize     = 268435456; //Should not exceed than this value ,i.e., 2^28 because verilog doesn't support more than 2^30
    
    reg[cacheElementSize-1:0] cacheMemory[index-1:0][k-1:0];
    reg [instructionSize-1:0] instructionMem[instructionMemSize-1:0];
    reg[byteToBits-1:0] mainMemory[mainMemorySize-1:0];
    reg[bitsOfk-1:0] cost[index-1:0][k-1:0];                                                //for LRU implementation
    reg [31:0] mem[523:0];
    
    input clk;
    reg [32+byteToBits:0] instruction;                                                               // 1 read/0write 32 address  16 bits block   ->   49 bits
    
    reg [sizeOfAddress-1:0] address;
    reg [15:0] dataToWrite;                                                                 // used in write instruction
    reg readWrite;
    
    reg[31:0] PC;
    reg[31:0] temp;
    reg isHit;
    integer i = 0;
    integer j = 0;
    integer locationOfHit;
    integer writeOnMiss;
    integer countHit,countMiss,countTotal;
    integer fd = 0;
    integer rv = 0;
    integer o,p;
    
    reg[blockSize*byteToBits-1:0] dataFromMainMemory;
    integer addressForReadWhileHit;
    
    initial begin
        countHit           = 0;
        countMiss          = 0;
        countTotal         = 0;
        PC                 = 0;
        readWrite          = 0;
        dataToWrite        = 0;
        dataFromMainMemory = 0;
        addressForReadWhileHit=0;
        for(i = 0;i<index;i = i+1)begin
            for(j = 0;j<k;j = j+1) begin
                cost[i][j] = 0;
            end
        end
        for(i = 0;i<index;i = i+1)begin
            for(j = 0;j<k;j = j+1) begin
                cacheMemory[i][j] = 0;
            end
        end
        
        
        
        
        fd = $fopen("inst1.txt", "r");
        for (i = 0; i < instructionMemSize; i = i + 1)begin
            rv = $fscanf(fd, "%h",instructionMem[i]);
        end
        
    end
    
    // implementing cache
    always@(posedge clk)begin
        //code for instruction decode , comm
        instruction = instructionMem[PC];
        isHit <= 0;
        #0.5 begin
        readWrite   = instruction[instructionSize-1];
        address     = instruction[instructionSize-2:instructionSize-1-sizeOfAddress];
        dataToWrite = instruction[byteToBits-1:0];
        end
    
    //address = mem[PC];
    #2 for(i = 0;i<k;i = i+1)begin
    isHit = isHit||((cacheMemory[address[bitsOfIndex+bitsOfBlockSize-1:bitsOfBlockSize]][i][cacheElementSize-1]) && (address[sizeOfAddress-1:bitsOfBlockSize+bitsOfIndex] == cacheMemory[address[bitsOfIndex+bitsOfBlockSize-1:bitsOfBlockSize]][i][cacheElementSize-2:cacheElementSize-1-tag]));
    if ((cacheMemory[address[bitsOfIndex+bitsOfBlockSize-1:bitsOfBlockSize]][i][cacheElementSize-1]) && (address[sizeOfAddress-1:bitsOfBlockSize+bitsOfIndex] == cacheMemory[address[bitsOfIndex+bitsOfBlockSize-1:bitsOfBlockSize]][i][cacheElementSize-2:cacheElementSize-1-tag]))begin
        locationOfHit = i;
    end
    end
    
    
    
    #4 case(isHit)
    1'b1:begin
    //  address[bitsOfIndex+bitsOfBlockSize-1:bitsOfBlockSize]
    addressForReadWhileHit= wordSize*byteToBits*address[bitsOfBlockSize-1:0];  //addressForReadWhileHit+bytesToBits-1:addressForReadWhileHit
    for(i = 0;i<k;i = i+1)begin
        if (cacheMemory[address[bitsOfIndex+bitsOfBlockSize-1:bitsOfBlockSize]][i][cacheElementSize-1]&&(cost[address[bitsOfIndex+bitsOfBlockSize-1:bitsOfBlockSize]][i]<cost[address[bitsOfIndex+bitsOfBlockSize-1:bitsOfBlockSize]][locationOfHit]))begin
            cost[address[bitsOfIndex+bitsOfBlockSize-1:bitsOfBlockSize]][i] = cost[address[bitsOfIndex+bitsOfBlockSize-1:bitsOfBlockSize]][i]+1;
        end
        
    end
    cost[address[bitsOfIndex+bitsOfBlockSize-1:bitsOfBlockSize]][locationOfHit] = 0;
    end
    1'b0:begin
    addressForReadWhileHit= wordSize*byteToBits*address[bitsOfBlockSize-1:0];
    for(i = 0;i<k;i = i+1)begin
        if (cacheMemory[address[bitsOfIndex+bitsOfBlockSize-1:bitsOfBlockSize]][i][cacheElementSize-1])begin
            if (cost[address[bitsOfIndex+bitsOfBlockSize-1:bitsOfBlockSize]][i] != k-1) begin
                cost[address[bitsOfIndex+bitsOfBlockSize-1:bitsOfBlockSize]][i] = cost[address[bitsOfIndex+bitsOfBlockSize-1:bitsOfBlockSize]][i]+1;
            end
            else begin
                cost[address[bitsOfIndex+bitsOfBlockSize-1:bitsOfBlockSize]][i] = 0;
                writeOnMiss                                                     = i;
            end
        end
    end
    for(i = 0;i<k;i = i+1)begin
        if (~cacheMemory[address[bitsOfIndex+bitsOfBlockSize-1:bitsOfBlockSize]][i][cacheElementSize-1])begin
            cacheMemory[address[bitsOfIndex+bitsOfBlockSize-1:bitsOfBlockSize]][i][cacheElementSize-1] = 1;
            cost[address[bitsOfIndex+bitsOfBlockSize-1:bitsOfBlockSize]][i]                            = 0;
            writeOnMiss                                                                                = i;
            i                                                                                          = k;
        end
    end
    
    end
    
    endcase


    #6 case(isHit)
    1'b1: begin
    //RN we are just maintaining count of hit and miss and just updating cache
    countHit   = countHit+1;
    countTotal = countTotal+1;
    case (readWrite)
        1'b1:begin

            // cacheMemory[address[bitsOfIndex+bitsOfBlockSize-1:bitsOfBlockSize]][locationOfHit][ (blockSize*wordSize*bytesToBits) -1 :0 ];
        end
        1'b0:begin          
        end
    endcase
    end
    1'b0: begin
    
    countMiss                                                                        = countMiss+1;
    countTotal                                                                       = countTotal+1;
    cacheMemory[address[bitsOfIndex+bitsOfBlockSize-1:bitsOfBlockSize]][writeOnMiss] = {1'b1,address[sizeOfAddress-1:bitsOfBlockSize+bitsOfIndex], dataFromMainMemory};
    end
    endcase
    #8 PC = PC+1'd1;
    #8 $display("CountHit %d", countHit);
    #8 $display("CountMiss %d", countMiss);
    #8 $display("CountTotal %d", countTotal);
    #8 $display("HitPercentage %d", 100*countHit/countTotal);
    end
    
endmodule

CacheMemoryProjectWithMainMemory/tb.v
module tb();
reg clk;
initial begin
        $dumpfile("testbench.vcd");
        $dumpvars(0,tb);
        clk                  = 1;
        repeat(150000) #100 clk = ~clk;
    end
    memoryProject memoryProject(
        .clk(clk)
    );
endmodule

CacheMemoryProjectWithMainMemory/testbench.vcd
$date
	Sun Nov 13 23:16:02 2022
$end
$version
	Icarus Verilog
$end
$timescale
	1s
$end
$scope module tb $end
$var reg 1 ! clk $end
$scope module memoryProject $end
$var wire 1 ! clk $end
$var reg 32 " PC [31:0] $end
$var reg 32 # address [31:0] $end
$var reg 16 $ dataFromMainMemory [15:0] $end
$var reg 16 % dataToWrite [15:0] $end
$var reg 41 & instruction [40:0] $end
$var reg 1 ' isHit $end
$var reg 1 ( readWrite $end
$var integer 32 ) addressForReadWhileHit [31:0] $end
$var integer 32 * countHit [31:0] $end
$var integer 32 + countMiss [31:0] $end
$var integer 32 , countTotal [31:0] $end
$var integer 32 - fd [31:0] $end
$var integer 32 . i [31:0] $end
$var integer 32 / j [31:0] $end
$var integer 32 0 locationOfHit [31:0] $end
$var integer 32 1 rv [31:0] $end
$var integer 32 2 writeOnMiss [31:0] $end
$upscope $end
$upscope $end
$enddefinitions $end
#0
$dumpvars
bx 2
b1 1
bx 0
b1000 /
b1000001100 .
b10000000000000000000000000000011 -
b0 ,
b0 +
b0 *
b0 )
0(
0'
b1000000000000111111000011010001000 &
b0 %
b0 $
bx #
b0 "
1!
$end
#1
b10001000 %
b10000000000001111110000110 #
#3
b1000 .
#7
b0 2
b1001 .
#13
b1 ,
b1 +
#21
b1 "
#100
0!
#200
b100000000000000111010110100010011 &
1!
#201
b10011 %
b1000000000000001110101101 #
#203
b1000 .
#207
b1001 .
b1000 )
#213
b10 ,
b10 +
#221
b10 "
#300
0!
#400
b100000000000001101010000001010100 &
1!
#401
b1010100 %
b1000000000000011010100000 #
#403
b1000 .
#407
b1001 .
b0 )
#413
b11 ,
b11 +
#421
b11 "
#500
0!
#600
b1000000000000111111000010100111111 &
1!
#601
b111111 %
b10000000000001111110000101 #
#603
b1000 .
#607
b1001 .
b1000 )
#613
b100 ,
b100 +
#621
b100 "
#700
0!
#800
b1000000000000111110111000100011101 &
1!
#801
b11101 %
b10000000000001111101110001 #
#803
b1000 .
#807
b1001 .
#813
b101 ,
b101 +
#821
b101 "
#900
0!
#1000
b1000000000000111110111010010111000 &
1!
#1001
b10111000 %
b10000000000001111101110100 #
#1003
b1000 .
#1007
b1001 .
b0 )
#1013
b110 ,
b110 +
#1021
b110 "
#1100
0!
#1200
b100000000000001000010111101011011 &
1!
#1201
b1011011 %
b1000000000000010000101111 #
#1203
b1000 .
#1207
b1001 .
b1000 )
#1213
b111 ,
b111 +
#1221
b111 "
#1300
0!
#1400
b1000000000000111110110110110111101 &
1!
#1401
b10111101 %
b10000000000001111101101101 #
#1403
b1000 .
#1407
b1001 .
#1413
b1000 ,
b1000 +
#1421
b1000 "
#1500
0!
#1600
b1000000000000111110110111010011101 &
1!
#1601
b10011101 %
b10000000000001111101101110 #
#1603
b1000 .
#1607
b1001 .
b0 )
#1613
b1001 ,
b1001 +
#1621
b1001 "
#1700
0!
#1800
b1000000000000111110111000010111000 &
1!
#1801
b10111000 %
b10000000000001111101110000 #
#1803
b0 0
1'
b1000 .
#1807
b1000 .
#1813
b1010 ,
b1 *
#1821
b1010 "
#1900
0!
#2000
0'
b100000000000000111100100000111111 &
1!
#2001
b111111 %
b1000000000000001111001000 #
#2003
b1000 .
#2007
b1001 .
#2013
b1011 ,
b1010 +
#2021
b1011 "
#2100
0!
#2200
b100000000000000111100011101111101 &
1!
#2201
b1111101 %
b1000000000000001111000111 #
#2203
b1000 .
#2207
b1001 .
b1000 )
#2213
b1100 ,
b1011 +
#2221
b1100 "
#2300
0!
#2400
b1000000000000111110110000010001111 &
1!
#2401
b10001111 %
b10000000000001111101100000 #
#2403
b1000 .
#2407
b1001 .
b0 )
#2413
b1101 ,
b1100 +
#2421
b1101 "
#2500
0!
#2600
b1000000000000111110110101101010011 &
1!
#2601
b1010011 %
b10000000000001111101101011 #
#2603
b1000 .
#2607
b1001 .
b1000 )
#2613
b1110 ,
b1101 +
#2621
b1110 "
#2700
0!
#2800
b100000000000000111010111000011110 &
1!
#2801
b11110 %
b1000000000000001110101110 #
#2803
b1000 .
#2807
b1 2
b1001 .
b0 )
#2813
b1111 ,
b1110 +
#2821
b1111 "
#2900
0!
#3000
b1000000000000111110110000111111001 &
1!
#3001
b11111001 %
b10000000000001111101100001 #
#3003
1'
b1000 .
#3007
b1000 .
b1000 )
#3013
b10000 ,
b10 *
#3021
b10000 "
#3100
0!
#3200
0'
b1000000000000111110110101010100111 &
1!
#3201
b10100111 %
b10000000000001111101101010 #
#3203
1'
b1000 .
#3207
b1000 .
b0 )
#3213
b10001 ,
b11 *
#3221
b10001 "
#3300
0!
#3400
0'
b100000000000001000100000010111010 &
1!
#3401
b10111010 %
b1000000000000010001000000 #
#3403
b1000 .
#3407
b0 2
b1001 .
#3413
b10010 ,
b1111 +
#3421
b10010 "
#3500
0!
#3600
b100000000000001001001100010011110 &
1!
#3601
b10011110 %
b1000000000000010010011000 #
#3603
b1000 .
#3607
b1001 .
#3613
b10011 ,
b10000 +
#3621
b10011 "
#3700
0!
#3800
b1000000000000111110111010111001110 &
1!
#3801
b11001110 %
b10000000000001111101110101 #
#3803
1'
b1000 .
#3807
b1000 .
b1000 )
#3813
b10100 ,
b100 *
#3821
b10100 "
#3900
0!
#4000
0'
b100000000000001001001100100000000 &
1!
#4001
b0 %
b1000000000000010010011001 #
#4003
1'
b1000 .
#4007
b1000 .
#4013
b10101 ,
b101 *
#4021
b10101 "
#4100
0!
#4200
0'
b1000000000000111110111011011110010 &
1!
#4201
b11110010 %
b10000000000001111101110110 #
#4203
b1000 .
#4207
b1001 .
b0 )
#4213
b10110 ,
b10001 +
#4221
b10110 "
#4300
0!
#4400
b100000000000001001001101001000100 &
1!
#4401
b1000100 %
b1000000000000010010011010 #
#4403
b1000 .
#4407
b1001 .
#4413
b10111 ,
b10010 +
#4421
b10111 "
#4500
0!
#4600
b100000000000000000000001111111001 &
1!
#4601
b11111001 %
b1000000000000000000000011 #
#4603
b1000 .
#4607
b1001 .
b1000 )
#4613
b11000 ,
b10011 +
#4621
b11000 "
#4700
0!
#4800
b100000000000000000000001001100001 &
1!
#4801
b1100001 %
b1000000000000000000000010 #
#4803
1'
b1000 .
#4807
b1000 .
b0 )
#4813
b11001 ,
b110 *
#4821
b11001 "
#4900
0!
#5000
0'
b1000000000000111110111000101000011 &
1!
#5001
b1000011 %
b10000000000001111101110001 #
#5003
1'
b1000 .
#5007
b1000 .
b1000 )
#5013
b11010 ,
b111 *
#5021
b11010 "
#5100
0!
#5200
0'
b1000000000000111110111010000000001 &
1!
#5201
b1 %
b10000000000001111101110100 #
#5203
1'
b1000 .
#5207
b1000 .
b0 )
#5213
b11011 ,
b1000 *
#5221
b11011 "
#5300
0!
#5400
0'
b100000000000001000010111111101100 &
1!
#5401
b11101100 %
b1000000000000010000101111 #
#5403
1'
b1000 .
#5407
b1000 .
b1000 )
#5413
b11100 ,
b1001 *
#5421
b11100 "
#5500
0!
#5600
0'
b1000000000000111110110110111010001 &
1!
#5601
b11010001 %
b10000000000001111101101101 #
#5603
1'
b1000 .
#5607
b1000 .
#5613
b11101 ,
b1010 *
#5621
b11101 "
#5700
0!
#5800
0'
b1000000000000111110110111001011111 &
1!
#5801
b1011111 %
b10000000000001111101101110 #
#5803
1'
b1000 .
#5807
b1000 .
b0 )
#5813
b11110 ,
b1011 *
#5821
b11110 "
#5900
0!
#6000
0'
b1000000000000111110111000010101010 &
1!
#6001
b10101010 %
b10000000000001111101110000 #
#6003
1'
b1000 .
#6007
b1000 .
#6013
b11111 ,
b1100 *
#6021
b11111 "
#6100
0!
#6200
0'
b100000000000000111100100011101101 &
1!
#6201
b11101101 %
b1000000000000001111001000 #
#6203
1'
b1000 .
#6207
b1000 .
#6213
b100000 ,
b1101 *
#6221
b100000 "
#6300
0!
#6400
0'
b100000000000000111100011100010101 &
1!
#6401
b10101 %
b1000000000000001111000111 #
#6403
1'
b1000 .
#6407
b1000 .
b1000 )
#6413
b100001 ,
b1110 *
#6421
b100001 "
#6500
0!
#6600
0'
b100000000000001001001101110110111 &
1!
#6601
b10110111 %
b1000000000000010010011011 #
#6603
1'
b1000 .
#6607
b1000 .
#6613
b100010 ,
b1111 *
#6621
b100010 "
#6700
0!
#6800
0'
b100000000000001001001110010101011 &
1!
#6801
b10101011 %
b1000000000000010010011100 #
#6803
b1000 .
#6807
b1001 .
b0 )
#6813
b100011 ,
b10100 +
#6821
b100011 "
#6900
0!
#7000
b1000000000000111110111001001111101 &
1!
#7001
b1111101 %
b10000000000001111101110010 #
#7003
b1000 .
#7007
b1001 .
#7013
b100100 ,
b10101 +
#7021
b100100 "
#7100
0!
#7200
b100000000000000111010111000011011 &
1!
#7201
b11011 %
b1000000000000001110101110 #
#7203
b1 0
1'
b1000 .
#7207
b1000 .
#7213
b100101 ,
b10000 *
#7221
b100101 "
#7300
0!
#7400
0'
b100000000000001001001110101011110 &
1!
#7401
b1011110 %
b1000000000000010010011101 #
#7403
b0 0
1'
b1000 .
#7407
b1000 .
b1000 )
#7413
b100110 ,
b10001 *
#7421
b100110 "
#7500
0!
#7600
0'
b100000000000001001001111011010001 &
1!
#7601
b11010001 %
b1000000000000010010011110 #
#7603
b1000 .
#7607
b1001 .
b0 )
#7613
b100111 ,
b10110 +
#7621
b100111 "
#7700
0!
#7800
b100000000000001001001111101010010 &
1!
#7801
b1010010 %
b1000000000000010010011111 #
#7803
1'
b1000 .
#7807
b1000 .
b1000 )
#7813
b101000 ,
b10010 *
#7821
b101000 "
#7900
0!
#8000
0'
b1000000000000111110111010101101111 &
1!
#8001
b1101111 %
b10000000000001111101110101 #
#8003
1'
b1000 .
#8007
b1000 .
#8013
b101001 ,
b10011 *
#8021
b101001 "
#8100
0!
#8200
0'
b100000000000001001010000011001011 &
1!
#8201
b11001011 %
b1000000000000010010100000 #
#8203
b1000 .
#8207
b1 2
b1001 .
b0 )
#8213
b101010 ,
b10111 +
#8221
b101010 "
#8300
0!
#8400
b1000000000000111110111011000000011 &
1!
#8401
b11 %
b10000000000001111101110110 #
#8403
1'
b1000 .
#8407
b1000 .
#8413
b101011 ,
b10100 *
#8421
b101011 "
#8500
0!
#8600
0'
b100000000000001001010000100101101 &
1!
#8601
b101101 %
b1000000000000010010100001 #
#8603
b1 0
1'
b1000 .
#8607
b1000 .
b1000 )
#8613
b101100 ,
b10101 *
#8621
b101100 "
#8700
0!
#8800
0'
b100000000000001001010001000100010 &
1!
#8801
b100010 %
b1000000000000010010100010 #
#8803
b1000 .
#8807
b0 2
b1001 .
b0 )
#8813
b101101 ,
b11000 +
#8821
b101101 "
#8900
0!
#9000
b100000000000000000000001110101010 &
1!
#9001
b10101010 %
b1000000000000000000000011 #
#9003
b0 0
1'
b1000 .
#9007
b1000 .
b1000 )
#9013
b101110 ,
b10110 *
#9021
b101110 "
#9100
0!
#9200
0'
b100000000000000000000001010110101 &
1!
#9201
b10110101 %
b1000000000000000000000010 #
#9203
1'
b1000 .
#9207
b1000 .
b0 )
#9213
b101111 ,
b10111 *
#9221
b101111 "
#9300
0!
#9400
0'
b1000000000000111110111010000001011 &
1!
#9401
b1011 %
b10000000000001111101110100 #
#9403
1'
b1000 .
#9407
b1000 .
#9413
b110000 ,
b11000 *
#9421
b110000 "
#9500
0!
#9600
0'
b1000000000000111110111000100110001 &
1!
#9601
b110001 %
b10000000000001111101110001 #
#9603
1'
b1000 .
#9607
b1000 .
b1000 )
#9613
b110001 ,
b11001 *
#9621
b110001 "
#9700
0!
#9800
0'
b100000000000001000010111110000100 &
1!
#9801
b10000100 %
b1000000000000010000101111 #
#9803
1'
b1000 .
#9807
b1000 .
#9813
b110010 ,
b11010 *
#9821
b110010 "
#9900
0!
#10000
0'
b1000000000000111110110110110010101 &
1!
#10001
b10010101 %
b10000000000001111101101101 #
#10003
1'
b1000 .
#10007
b1000 .
#10013
b110011 ,
b11011 *
#10021
b110011 "
#10100
0!
#10200
0'
b1000000000000111110110111001011000 &
1!
#10201
b1011000 %
b10000000000001111101101110 #
#10203
1'
b1000 .
#10207
b1000 .
b0 )
#10213
b110100 ,
b11100 *
#10221
b110100 "
#10300
0!
#10400
0'
b1000000000000111110111000010111001 &
1!
#10401
b10111001 %
b10000000000001111101110000 #
#10403
1'
b1000 .
#10407
b1000 .
#10413
b110101 ,
b11101 *
#10421
b110101 "
#10500
0!
#10600
0'
b100000000000000111100100001100010 &
1!
#10601
b1100010 %
b1000000000000001111001000 #
#10603
1'
b1000 .
#10607
b1000 .
#10613
b110110 ,
b11110 *
#10621
b110110 "
#10700
0!
#10800
0'
b100000000000000111100011100110100 &
1!
#10801
b110100 %
b1000000000000001111000111 #
#10803
1'
b1000 .
#10807
b1000 .
b1000 )
#10813
b110111 ,
b11111 *
#10821
b110111 "
#10900
0!
#11000
0'
b100000000000001001010001100010000 &
1!
#11001
b10000 %
b1000000000000010010100011 #
#11003
1'
b1000 .
#11007
b1000 .
#11013
b111000 ,
b100000 *
#11021
b111000 "
#11100
0!
#11200
0'
b100000000000001001010010001000110 &
1!
#11201
b1000110 %
b1000000000000010010100100 #
#11203
b1000 .
#11207
b1001 .
b0 )
#11213
b111001 ,
b11001 +
#11221
b111001 "
#11300
0!
#11400
b1000000000000111110111001111110001 &
1!
#11401
b11110001 %
b10000000000001111101110011 #
#11403
1'
b1000 .
#11407
b1000 .
b1000 )
#11413
b111010 ,
b100001 *
#11421
b111010 "
#11500
0!
#11600
0'
b100000000000000111010111010101111 &
1!
#11601
b10101111 %
b1000000000000001110101110 #
#11603
b1 0
1'
b1000 .
#11607
b1000 .
b0 )
#11613
b111011 ,
b100010 *
#11621
b111011 "
#11700
0!
#11800
0'
b100000000000001001010010111001011 &
1!
#11801
b11001011 %
b1000000000000010010100101 #
#11803
b0 0
1'
b1000 .
#11807
b1000 .
b1000 )
#11813
b111100 ,
b100011 *
#11821
b111100 "
#11900
0!
#12000
0'
b100000000000001001010011011110011 &
1!
#12001
b11110011 %
b1000000000000010010100110 #
#12003
b1000 .
#12007
b1001 .
b0 )
#12013
b111101 ,
b11010 +
#12021
b111101 "
#12100
0!
#12200
b100000000000001001010011110101001 &
1!
#12201
b10101001 %
b1000000000000010010100111 #
#12203
1'
b1000 .
#12207
b1000 .
b1000 )
#12213
b111110 ,
b100100 *
#12221
b111110 "
#12300
0!
#12400
0'
b1000000000000111110111010100100100 &
1!
#12401
b100100 %
b10000000000001111101110101 #
#12403
1'
b1000 .
#12407
b1000 .
#12413
b111111 ,
b100101 *
#12421
b111111 "
#12500
0!
#12600
0'
b100000000000001001010100011011110 &
1!
#12601
b11011110 %
b1000000000000010010101000 #
#12603
b1000 .
#12607
b1001 .
b0 )
#12613
b1000000 ,
b11011 +
#12621
b1000000 "
#12700
0!
#12800
b1000000000000111110111011010001001 &
1!
#12801
b10001001 %
b10000000000001111101110110 #
#12803
1'
b1000 .
#12807
b1000 .
#12813
b1000001 ,
b100110 *
#12821
b1000001 "
#12900
0!
#13000
0'
b100000000000001001010100110011000 &
1!
#13001
b10011000 %
b1000000000000010010101001 #
#13003
1'
b1000 .
#13007
b1000 .
b1000 )
#13013
b1000010 ,
b100111 *
#13021
b1000010 "
#13100
0!
#13200
0'
b100000000000001001010101001011011 &
1!
#13201
b1011011 %
b1000000000000010010101010 #
#13203
b1000 .
#13207
b1001 .
b0 )
#13213
b1000011 ,
b11100 +
#13221
b1000011 "
#13300
0!
#13400
b100000000000000000000001101100100 &
1!
#13401
b1100100 %
b1000000000000000000000011 #
#13403
1'
b1000 .
#13407
b1000 .
b1000 )
#13413
b1000100 ,
b101000 *
#13421
b1000100 "
#13500
0!
#13600
0'
b1000000000000111110111010000011110 &
1!
#13601
b11110 %
b10000000000001111101110100 #
#13603
1'
b1000 .
#13607
b1000 .
b0 )
#13613
b1000101 ,
b101001 *
#13621
b1000101 "
#13700
0!
#13800
0'
b100000000000000000000001010101111 &
1!
#13801
b10101111 %
b1000000000000000000000010 #
#13803
1'
b1000 .
#13807
b1000 .
#13813
b1000110 ,
b101010 *
#13821
b1000110 "
#13900
0!
#14000
0'
b1000000000000111110111000111000010 &
1!
#14001
b11000010 %
b10000000000001111101110001 #
#14003
1'
b1000 .
#14007
b1000 .
b1000 )
#14013
b1000111 ,
b101011 *
#14021
b1000111 "
#14100
0!
#14200
0'
b100000000000001000010111100110110 &
1!
#14201
b110110 %
b1000000000000010000101111 #
#14203
1'
b1000 .
#14207
b1000 .
#14213
b1001000 ,
b101100 *
#14221
b1001000 "
#14300
0!
#14400
0'
b1000000000000111110110110111011110 &
1!
#14401
b11011110 %
b10000000000001111101101101 #
#14403
1'
b1000 .
#14407
b1000 .
#14413
b1001001 ,
b101101 *
#14421
b1001001 "
#14500
0!
#14600
0'
b1000000000000111110110111010001001 &
1!
#14601
b10001001 %
b10000000000001111101101110 #
#14603
1'
b1000 .
#14607
b1000 .
b0 )
#14613
b1001010 ,
b101110 *
#14621
b1001010 "
#14700
0!
#14800
0'
b1000000000000111110111000000000011 &
1!
#14801
b11 %
b10000000000001111101110000 #
#14803
1'
b1000 .
#14807
b1000 .
#14813
b1001011 ,
b101111 *
#14821
b1001011 "
#14900
0!
#15000
0'
b100000000000000111100100010100101 &
1!
#15001
b10100101 %
b1000000000000001111001000 #
#15003
1'
b1000 .
#15007
b1000 .
#15013
b1001100 ,
b110000 *
#15021
b1001100 "
#15100
0!
#15200
0'
b100000000000000111100011111111010 &
1!
#15201
b11111010 %
b1000000000000001111000111 #
#15203
1'
b1000 .
#15207
b1000 .
b1000 )
#15213
b1001101 ,
b110001 *
#15221
b1001101 "
#15300
0!
#15400
0'
b100000000000001001010101111000100 &
1!
#15401
b11000100 %
b1000000000000010010101011 #
#15403
1'
b1000 .
#15407
b1000 .
#15413
b1001110 ,
b110010 *
#15421
b1001110 "
#15500
0!
#15600
0'
b100000000000001001010110001100100 &
1!
#15601
b1100100 %
b1000000000000010010101100 #
#15603
b1000 .
#15607
b1 2
b1001 .
b0 )
#15613
b1001111 ,
b11101 +
#15621
b1001111 "
#15700
0!
#15800
b1000000000000111110110101110101100 &
1!
#15801
b10101100 %
b10000000000001111101101011 #
#15803
1'
b1000 .
#15807
b1000 .
b1000 )
#15813
b1010000 ,
b110011 *
#15821
b1010000 "
#15900
0!
#16000
0'
b1000000000000111110110110001001110 &
1!
#16001
b1001110 %
b10000000000001111101101100 #
#16003
1'
b1000 .
#16007
b1000 .
b0 )
#16013
b1010001 ,
b110100 *
#16021
b1010001 "
#16100
0!
#16200
0'
b1000000000000111110110101010111101 &
1!
#16201
b10111101 %
b10000000000001111101101010 #
#16203
1'
b1000 .
#16207
b1000 .
#16213
b1010010 ,
b110101 *
#16221
b1010010 "
#16300
0!
#16400
0'
b1000000000000111110110100110000001 &
1!
#16401
b10000001 %
b10000000000001111101101001 #
#16403
b1000 .
#16407
b0 2
b1001 .
b1000 )
#16413
b1010011 ,
b11110 +
#16421
b1010011 "
#16500
0!
#16600
b1000000000000111110110100001101001 &
1!
#16601
b1101001 %
b10000000000001111101101000 #
#16603
1'
b1000 .
#16607
b1000 .
b0 )
#16613
b1010100 ,
b110110 *
#16621
b1010100 "
#16700
0!
#16800
0'
b1000000000000111110110011111010011 &
1!
#16801
b11010011 %
b10000000000001111101100111 #
#16803
b1000 .
#16807
b1001 .
b1000 )
#16813
b1010101 ,
b11111 +
#16821
b1010101 "
#16900
0!
#17000
b1000000000000111110110011011011001 &
1!
#17001
b11011001 %
b10000000000001111101100110 #
#17003
1'
b1000 .
#17007
b1000 .
b0 )
#17013
b1010110 ,
b110111 *
#17021
b1010110 "
#17100
0!
#17200
0'
b1000000000000111110111001110111010 &
1!
#17201
b10111010 %
b10000000000001111101110011 #
#17203
1'
b1000 .
#17207
b1000 .
b1000 )
#17213
b1010111 ,
b111000 *
#17221
b1010111 "
#17300
0!
#17400
0'
b1000000000000111110111001001001101 &
1!
#17401
b1001101 %
b10000000000001111101110010 #
#17403
1'
b1000 .
#17407
b1000 .
b0 )
#17413
b1011000 ,
b111001 *
#17421
b1011000 "
#17500
0!
#17600
0'
b1000000000000111110110010100001000 &
1!
#17601
b1000 %
b10000000000001111101100101 #
#17603
b1000 .
#17607
b1001 .
b1000 )
#17613
b1011001 ,
b100000 +
#17621
b1011001 "
#17700
0!
#17800
b1000000000000111110110001110011100 &
1!
#17801
b10011100 %
b10000000000001111101100011 #
#17803
b1000 .
#17807
b1001 .
#17813
b1011010 ,
b100001 +
#17821
b1011010 "
#17900
0!
#18000
b1000000000000111110110001001110111 &
1!
#18001
b1110111 %
b10000000000001111101100010 #
#18003
1'
b1000 .
#18007
b1000 .
b0 )
#18013
b1011011 ,
b111010 *
#18021
b1011011 "
#18100
0!
#18200
0'
b1000000000000111110110000100110100 &
1!
#18201
b110100 %
b10000000000001111101100001 #
#18203
1'
b1000 .
#18207
b1000 .
b1000 )
#18213
b1011100 ,
b111011 *
#18221
b1011100 "
#18300
0!
#18400
0'
b1000000000000111110110010011110100 &
1!
#18401
b11110100 %
b10000000000001111101100100 #
#18403
1'
b1000 .
#18407
b1000 .
b0 )
#18413
b1011101 ,
b111100 *
#18421
b1011101 "
#18500
0!
#18600
0'
b1000000000000111110111000111111100 &
1!
#18601
b11111100 %
b10000000000001111101110001 #
#18603
1'
b1000 .
#18607
b1000 .
b1000 )
#18613
b1011110 ,
b111101 *
#18621
b1011110 "
#18700
0!
#18800
0'
b1000000000000111110111010000010101 &
1!
#18801
b10101 %
b10000000000001111101110100 #
#18803
1'
b1000 .
#18807
b1000 .
b0 )
#18813
b1011111 ,
b111110 *
#18821
b1011111 "
#18900
0!
#19000
0'
b1000000000000111110110110100110001 &
1!
#19001
b110001 %
b10000000000001111101101101 #
#19003
1'
b1000 .
#19007
b1000 .
b1000 )
#19013
b1100000 ,
b111111 *
#19021
b1100000 "
#19100
0!
#19200
0'
b100000000000001000010111111101101 &
1!
#19201
b11101101 %
b1000000000000010000101111 #
#19203
1'
b1000 .
#19207
b1000 .
#19213
b1100001 ,
b1000000 *
#19221
b1100001 "
#19300
0!
#19400
0'
b1000000000000111110110111001101101 &
1!
#19401
b1101101 %
b10000000000001111101101110 #
#19403
1'
b1000 .
#19407
b1000 .
b0 )
#19413
b1100010 ,
b1000001 *
#19421
b1100010 "
#19500
0!
#19600
0'
b1000000000000111110111000010001001 &
1!
#19601
b10001001 %
b10000000000001111101110000 #
#19603
1'
b1000 .
#19607
b1000 .
#19613
b1100011 ,
b1000010 *
#19621
b1100011 "
#19700
0!
#19800
0'
b100000000000000111100100100101100 &
1!
#19801
b101100 %
b1000000000000001111001001 #
#19803
1'
b1000 .
#19807
b1000 .
b1000 )
#19813
b1100100 ,
b1000011 *
#19821
b1100100 "
#19900
0!
#20000
0'
b1000000000000111110110111111000001 &
1!
#20001
b11000001 %
b10000000000001111101101111 #
#20003
1'
b1000 .
#20007
b1000 .
#20013
b1100101 ,
b1000100 *
